{"id":1,"userName":"asd","type":200,"content":""}
{"id":2,"userName":"WeeRacoon","type":200,"content":""}
{"id":3,"userName":"WeeRacoon","type":101,"content":"hola "}
{"id":1,"userName":"javaIloveItOMG","type":200,"content":""}
{"id":2,"userName":"javaIloveItOMG","type":101,"content":"tttttttttttttttttttttttttttttttttttttttttttttt"}
{"id":3,"userName":"javaIloveItOMG","type":101,"content":"😘😘😘😘"}
{"id":4,"userName":"adri","type":200,"content":""}
{"id":5,"userName":"adri","type":101,"content":"8=====3"}
{"id":1,"userName":"WeeRacoon","type":200,"content":""}
{"id":2,"userName":"WeeRacoon","type":101,"content":"asd"}
{"id":3,"userName":"WeeRacoon","type":101,"content":"asdadaaaaaaaaaaaaa"}
{"id":4,"userName":"WeeRacoon","type":200,"content":""}
{"id":1,"userName":"a","type":200,"content":""}
{"id":2,"userName":"a","type":101,"content":"asdasdasdaaaaaaaaaaaaaaaaaaaaaaaaaaaaaaaaaaaaaaaaa"}
{"id":1,"userName":"as","type":200,"content":""}
{"id":2,"userName":"as","type":101,"content":"asd"}
{"id":3,"userName":"asd","type":200,"content":""}
{"id":1,"userName":"a","type":200,"content":""}
{"id":1,"userName":"as","type":200,"content":""}
{"id":1,"userName":"asd","type":200,"content":""}
{"id":1,"userName":"asd","type":200,"content":""}
